scanports_pkg/__init__.py
scanports_pkg/scanPorts.py
scanports_pkg-0.1.1.data/scripts/scanPorts.py
scanports_pkg-0.1.1.dist-info/METADATA
scanports_pkg-0.1.1.dist-info/WHEEL
scanports_pkg-0.1.1.dist-info/entry_points.txt
scanports_pkg-0.1.1.dist-info/top_level.txt
scanports_pkg-0.1.1.dist-info/RECORD
