Metadata-Version: 2.1
Name: scanports-pkg
Version: 0.1.1
Summary: Analyze the format of all files in the given path
Home-page: https://github.com/zdf123zdf/scanports
Author: zdfzdf
Author-email: 2239432836@qq.com
License: UNKNOWN
Platform: UNKNOWN
Classifier: Programming Language :: Python :: 3
Classifier: License :: OSI Approved :: MIT License
Classifier: Operating System :: OS Independent
Requires-Dist: async-timeout
